MANIFEST.in
requirements.txt
setup.py
uvhue/__init__.py
uvhue/rgb.py
uvhue/utils.py
uvhue/uvhue.py
uvhue.egg-info/PKG-INFO
uvhue.egg-info/SOURCES.txt
uvhue.egg-info/dependency_links.txt
uvhue.egg-info/requires.txt
uvhue.egg-info/top_level.txt