Metadata-Version: 1.0
Name: uvhue
Version: 0.2
Summary: Hue client for uvhttp
Home-page: https://github.com/justinbarrick/uvhue
Author: UNKNOWN
Author-email: UNKNOWN
License: UNKNOWN
Platform: UNKNOWN
